{
    "gender": "unknown",
    "markersets": [
        {
            "distance_from_skin": 0.0095,
            "indices": {
                "C7": 3832,
                "CLAV": 5533,
                "LANK": 5882,
                "LFWT": 3486,
                "LBAK": 3336,
                "LBCEP": 4029,
                "LBSH": 4137,
                "LBUM": 5694,
                "LBUST": 3228,
                "LCHEECK": 2081,
                "LELB": 4302,
                "LELBIN": 4363,
                "LFIN": 4788,
                "LFRM2": 4379,
                "LFTHI": 3504,
                "LFTHIIN": 3998,
                "LHEE": 8846,
                "LIWR": 4726,
                "LKNE": 3682,
                "LKNI": 3688,
                "LMT1": 5890,
                "LMT5": 5901,
                "LNWST": 3260,
                "LOWR": 4722,
                "LBWT": 5697,
                "LRSTBEEF": 5838,
                "LSHO": 4481,
                "LTHI": 4088,
                "LTHMB": 4839,
                "LTIB": 3745,
                "LTOE": 5787,
                "MBLLY": 5942,
                "RANK": 8576,
                "RFWT": 6248,
                "RBAK": 6127,
                "RBCEP": 6776,
                "RBSH": 7192,
                "RBUM": 8388,
                "RBUSTLO": 8157,
                "RCHEECK": 8786,
                "RELB": 7040,
                "RELBIN": 7099,
                "RFIN": 7524,
                "RFRM2": 7115,
                "RFRM2IN": 7303,
                "RFTHI": 6265,
                "RFTHIIN": 6746,
                "RHEE": 8634,
                "RKNE": 6443,
                "RKNI": 6449,
                "RMT1": 8584,
                "RMT5": 8595,
                "RNWST": 6023,
                "ROWR": 7458,
                "RBWT": 8391,
                "RRSTBEEF": 8532,
                "RSHO": 6627,
                "RTHI": 6832,
                "RTHMB": 7575,
                "RTIB": 6503,
                "RTOE": 8481,
                "STRN": 5531,
                "T8": 5487,
                "LFHD": 707,
                "LBHD": 2026,
                "RFHD": 2198,
                "RBHD": 3066,
                "CHN1": 8757,
                "CHN2": 9066,
                "MTH3": 8985,
                "MTH7": 8947,
                "LIDX3": 4931,
                "LMID3": 5045,
                "LPNK3": 5268,
                "LRNG3": 5149,
                "LTHM4": 5346,
                "RIDX3": 7667,
                "RMID3": 7781,
                "RPNK3": 8001,
                "RRNG3": 7884,
                "RTHM4": 8082
            },
            "marker_radius": 0.0095,
            "type": "body"
        }
    ]
}